slidec/__init__.py
slidec/slidec.py
slidec-0.1.0.dist-info/LICENSE
slidec-0.1.0.dist-info/METADATA
slidec-0.1.0.dist-info/WHEEL
slidec-0.1.0.dist-info/entry_points.txt
slidec-0.1.0.dist-info/top_level.txt
slidec-0.1.0.dist-info/RECORD
