Metadata-Version: 2.1
Name: slidec
Version: 0.1.0
Summary: A Terminal-based Markdown Slide Presenter.
Author: Phil Whybra
License: MIT
Project-URL: Source, https://github.com/pwhybra/slidec
Keywords: terminal slides
Classifier: Programming Language :: Python :: 3
Classifier: License :: OSI Approved :: MIT License
Requires-Python: >=3.11
License-File: LICENSE
Requires-Dist: rich
Requires-Dist: readchar
